odoo/addons/calendar_activity_event_done/README.rst
odoo/addons/calendar_activity_event_done/__init__.py
odoo/addons/calendar_activity_event_done/__manifest__.py
odoo/addons/calendar_activity_event_done/i18n/es.po
odoo/addons/calendar_activity_event_done/models/__init__.py
odoo/addons/calendar_activity_event_done/models/calendar_event.py
odoo/addons/calendar_activity_event_done/models/mail_activity.py
odoo/addons/calendar_activity_event_done/readme/CONTRIBUTORS.md
odoo/addons/calendar_activity_event_done/readme/DESCRIPTION.md
odoo/addons/calendar_activity_event_done/readme/USAGE.md
odoo/addons/calendar_activity_event_done/static/description/icon.png
odoo/addons/calendar_activity_event_done/static/description/index.html
odoo/addons/calendar_activity_event_done/tests/__init__.py
odoo/addons/calendar_activity_event_done/tests/test_calendar_activity_event_done.py
odoo/addons/calendar_activity_event_done/views/calendar_event_views.xml
odoo_addon_calendar_activity_event_done-15.0.1.0.0.1.dist-info/METADATA
odoo_addon_calendar_activity_event_done-15.0.1.0.0.1.dist-info/WHEEL
odoo_addon_calendar_activity_event_done-15.0.1.0.0.1.dist-info/top_level.txt
odoo_addon_calendar_activity_event_done-15.0.1.0.0.1.dist-info/RECORD
