Metadata-Version: 2.1
Name: odoo-addon-calendar_activity_event_done
Version: 15.0.1.0.0.1
Summary: Calendar events linked with done activities will be shown as done
Home-page: https://github.com/sygel-technology/sy-calendar
Author: Sygel, Odoo Community Association (OCA)
Author-email: support@odoo-community.org
License: AGPL-3
Classifier: Programming Language :: Python
Classifier: Framework :: Odoo
Classifier: Framework :: Odoo :: 15.0
Classifier: License :: OSI Approved :: GNU Affero General Public License v3
Requires-Python: >=3.8
Requires-Dist: odoo<15.1dev,>=15.0a
